per4m/__init__.py
per4m/__main__.py
per4m/bla.py
per4m/cellmagic.py
per4m/example1.py
per4m/example2.py
per4m/example3.py
per4m/example4.py
per4m/giltracer.py
per4m/offgil.py
per4m/perf2trace.py
per4m/perfutils.py
per4m/record.py
per4m/script.py
perfpy/__init__.py
perfpy/__main__.py
perfpy/example1.py
per4m-0.0.3.dist-info/METADATA
per4m-0.0.3.dist-info/WHEEL
per4m-0.0.3.dist-info/entry_points.txt
per4m-0.0.3.dist-info/top_level.txt
per4m-0.0.3.dist-info/RECORD
