Metadata-Version: 2.1
Name: per4m
Version: 0.0.3
Summary: Profiling and tracing information for Python using viztracer and perf, the GIL exposed.
Home-page: https://www.github.com/maartenbreddels/per4m
Author: Maarten A. Breddels
Author-email: maartenbreddels@gmail.com
License: MIT
Platform: UNKNOWN
